pahada/__init__.py
pahada/core.py
pahada-0.1.dist-info/METADATA
pahada-0.1.dist-info/WHEEL
pahada-0.1.dist-info/top_level.txt
pahada-0.1.dist-info/RECORD
