Metadata-Version: 2.4
Name: pahada
Version: 0.1
Summary: A simple Python library to generate multiplication tables
Author: Shrey
Requires-Python: >=3.6
Dynamic: author
Dynamic: requires-python
Dynamic: summary
